evaluations/__init__.py
evaluations/classification/__init__.py
evaluations/classification/accuracy.py
evaluations/classification/confusion_matrix.py
evaluations/kaggle_2020/__init__.py
evaluations/kaggle_2020/global_average_precision.py
evaluations/kaggle_2020/row_wise_micro_averaged_f1.py
evaluations/medical/__init__.py
evaluations/medical/concordance_index.py
evaluations/text_extraction/__init__.py
evaluations/text_extraction/jaccard_word_level.py
tests/classification/__init__.py
tests/classification/test_accuracy_score.py
tests/classification/test_confusion_matrix.py
tests/kaggle_2020/__init__.py
tests/kaggle_2020/test_global_average_precision_score.py
tests/kaggle_2020/test_row_wise_micro_averaged_f1_score.py
tests/medical/__init__.py
tests/medical/test_concordance_index.py
tests/text_extraction/__init__.py
tests/text_extraction/test_jaccard_word_level_score.py
tests/text_extraction/test_jaccard_word_level_similarity.py
evaluations-0.0.5.dist-info/LICENSE
evaluations-0.0.5.dist-info/METADATA
evaluations-0.0.5.dist-info/WHEEL
evaluations-0.0.5.dist-info/top_level.txt
evaluations-0.0.5.dist-info/RECORD
