Metadata-Version: 2.1
Name: evaluations
Version: 0.0.5
Summary: The library for models evaluation
Home-page: https://github.com/yisaienkov/evaluations
Author: Yaroslav Isaienkov
Author-email: oiuygl@gmail.com
License: UNKNOWN
Platform: UNKNOWN
Classifier: Programming Language :: Python :: 3
Classifier: License :: OSI Approved :: MIT License
Classifier: Operating System :: OS Independent
Requires-Python: >=3.6
Provides-Extra: tests
Requires-Dist: pytest ; extra == 'tests'
